mactop/__init__.py
mactop/mactop.py
mactop/mactop_CLI.py
mactop3D-1.0.0.dist-info/METADATA
mactop3D-1.0.0.dist-info/WHEEL
mactop3D-1.0.0.dist-info/top_level.txt
mactop3D-1.0.0.dist-info/RECORD
