Metadata-Version: 2.1
Name: mactop3D
Version: 1.0.0
Summary: deciphering chromatin domain, domain community and chromunity for 3D genome maps
Home-page: https://github.com/ydduanran/Mactop
Author: Ran Duan
Author-email: duanran@mail.ynu.edu.cn
License: MIT
